photorch/__init__.py
photorch/data/__init__.py
photorch/data/tests/__init__.py
photorch/data/tests/dfMAGIC043_lr.csv
photorch/data/tests/nonsteadystate_stomatalconductance.csv
photorch/data/tests/steadystate_stomatalconductance.csv
photorch/src/__init__.py
photorch/src/util.py
photorch/src/fvcb/__init__.py
photorch/src/fvcb/evaluate.py
photorch/src/fvcb/fitaci.py
photorch/src/fvcb/fvcbmodels.py
photorch/src/fvcb/initphotodata.py
photorch/src/prospect/__init__.py
photorch/src/prospect/inverseprospect.py
photorch/src/prospect/prospectmodels.py
photorch/src/stomatal/__init__.py
photorch/src/stomatal/evaluate.py
photorch/src/stomatal/fitstomatal.py
photorch/src/stomatal/initscdata.py
photorch/src/stomatal/stomatalmodels.py
photorch-1.4.7.dist-info/licenses/LICENSE
photorch-1.4.7.dist-info/METADATA
photorch-1.4.7.dist-info/WHEEL
photorch-1.4.7.dist-info/top_level.txt
photorch-1.4.7.dist-info/RECORD
