Metadata-Version: 2.4
Name: photorch
Version: 1.4.7
Summary: PhoTorch is Python-based software for robust fitting of photosynthesis and stomatal conductance models based on leaf-level gas exchange data. 
Author: Tong Lei, Kyle T. Rizzo, Brian N. Bailey
Classifier: Programming Language :: Python :: 3.10
Classifier: Intended Audience :: Science/Research
Classifier: License :: OSI Approved :: GNU General Public License v3 (GPLv3)
Requires-Python: >=3.6
License-File: LICENSE
Requires-Dist: torch
Requires-Dist: numpy
Requires-Dist: pandas
Requires-Dist: scipy
Requires-Dist: matplotlib
Dynamic: author
Dynamic: classifier
Dynamic: description
Dynamic: description-content-type
Dynamic: license-file
Dynamic: requires-dist
Dynamic: requires-python
Dynamic: summary
